project_generator/__init__.py
project_generator/main.py
project_generator/templates/main.py.mako
project_generator_nibata-0.0.4.dist-info/METADATA
project_generator_nibata-0.0.4.dist-info/WHEEL
project_generator_nibata-0.0.4.dist-info/entry_points.txt
project_generator_nibata-0.0.4.dist-info/top_level.txt
project_generator_nibata-0.0.4.dist-info/RECORD
